codetree/__init__.py
codetree/cli.py
codetree/config.py
codetree/fileutils.py
codetree/six.py
codetree/handlers/__init__.py
codetree/handlers/basic.py
codetree/handlers/bzr.py
codetree/handlers/charm.py
codetree/handlers/exceptions.py
codetree/handlers/git.py
codetree/handlers/utils.py
python_codetree-1.2.0.dist-info/LICENSE
python_codetree-1.2.0.dist-info/METADATA
python_codetree-1.2.0.dist-info/WHEEL
python_codetree-1.2.0.dist-info/entry_points.txt
python_codetree-1.2.0.dist-info/top_level.txt
python_codetree-1.2.0.dist-info/RECORD
