Metadata-Version: 2.1
Name: python-codetree
Version: 1.2.0
Summary: A code tree builder
Home-page: https://launchpad.net/codetree
License: UNKNOWN
Platform: UNKNOWN
Classifier: Programming Language :: Python
Classifier: License :: OSI Approved :: MIT License
Classifier: Topic :: Internet
Classifier: Topic :: Software Development :: Libraries :: Python Modules
Classifier: Intended Audience :: Developers
Requires-Dist: pyyaml
Requires-Dist: requests
Provides-Extra: tests
Requires-Dist: coverage (>=4.4) ; extra == 'tests'
Requires-Dist: flake8 ; extra == 'tests'
Requires-Dist: nose (>=1.3.7) ; extra == 'tests'
Requires-Dist: pip (>=9.0) ; extra == 'tests'
Requires-Dist: requests (>=2.18) ; extra == 'tests'
Requires-Dist: setuptools (>=36.0.1) ; extra == 'tests'
